{
        "radios": [
                {
                        "id": 1,
                        "name": "Sooriyan FM Sri Lanka",
                        "desc": "Sooriyan FM Sri Lanka",
                        "genre": "Music",
                        "streams": [
                                {
                                        "src": "http://www.sooriyanfm.lk/",
                                        "srcName": "na",
                                        "br": "64",
                                        "url": "http://104.238.193.114:7077/;?1468675983387.mp3"
                                },
                                {
                                        "src": "http://www.sooriyanfm.lk/",
                                        "srcName": "na",
                                        "br": "48",
                                        "url": "http://104.238.193.114:7086/;?1468676137518.mp3"
                                }
                        ],
                        "imageUrl": "http://www.sooriyanfm.lk/images/listenlivelogo.jpg",
                        "priority": 1
                },
                {
                        "id": 2,
                        "name": "Lankasri FM",
                        "desc": "Lankasri FM",
                        "genre": "Music",
                        "streams": [
                                {
                                        "src": "http://www.shoutcast.com/",
                                        "srcName": "Lankasri FM",
                                        "br":"128",
                                        "url":"http://149.202.121.175/live?icy=http"
                                },
                                {
                                        "src": "http://www.shoutcast.com/",
                                        "srcName": "Lankasri FM",
                                        "br": "64",
                                        "url": " http://149.202.121.140/live?icy=http"
                                },
                                {
                                        "src": "http://www.shoutcast.com/",
                                        "srcName": "Lankasri FM",
                                        "br": "32",
                                        "url": "http://46.105.43.114:8000/live?icy=http"
                                }
                        ],
                        "imageUrl": "http://assets.zoftcdn.com/branding/lankasrifm/f_fm_200_b.png",
                        "priority": 2
                },
                {
                        "id": 3,
                        "name": "Mukil App",
                        "desc": "Mukil App",
                        "genre": "Music",
                        "streams": [
                                 {
                                        "src": "http://www.shoutcast.com/",
                                        "srcName": "Mukil App",
                                        "br": "128",
                                        "url": "http://listen.shoutcast.com/mukilfmradio?icy=http"
                                },
                                {
                                        "src": "http://www.shoutcast.com/",
                                        "srcName": "Mukil App",
                                        "br": "64",
                                        "url": "http://46.105.44.132/live?icy=http"
                                }
                                
                        ],
                        "imageUrl": "http://mukilapp.com/mukil/img/basic/Mukil_We_logo_001.png",
                        "priority": 3
                },
                {
                        "id": 4,
                        "name": "IBC Tamil",
                        "desc": "IBC Tamil",
                        "genre": "Music",
                        "streams": [
                                {
                                        "src": "http://ibctamil.com/",
                                        "srcName": "IBC Tamil",
                                        "br": "128",
                                        "url": "http://38.96.148.226:6176/;stream.mp3"
                                }
                        ],
                        "imageUrl": "http://ibctamil.com/images/logo.png",
                        "priority": 4
                },
                {
                        "id": 5,
                        "name": "Tamil Flash",
                        "desc": "Tamil Falsh",
                        "genre": "Music",
                        "streams": [
                                {
                                        "src": "http://www.tffm24.com",
                                        "srcName": "Tamilflash",
                                        "br": "96",
                                        "url": "http://64.71.79.181:5070/;"
                                }
                        ],
                        "imageUrl": "http://www.tffm24.com/images/logos.png",
                        "priority": 5
                },
                {
                        "id": 6,
                        "name": "Puradsi FM",
                        "desc": "Puradsi FM",
                        "genre": "Music",
                        "streams": [
                                {
                                        "src": "http://www.puradsifm.com/",
                                        "srcName": "Puradsi FM",
                                        "br": "128",
                                        "url": "http://puradsifm.net:9994/;"
                                }
                        ],
                        "imageUrl": "puradsi-isaiyaruvi",
                        "priority": 6
                },
                {
                        "id": 7,
                        "name": "TRT Tamil Olli",
                        "desc": "TRT Tamil Olli",
                        "genre": "Music",
                        "streams": [
                                {
                                        "src": "http://www.tamilolli.com/",
                                        "srcName": "TRT Tamil Olli",
                                        "br": "320",
                                        "url": "http://91.121.165.41:9035/stream.mp3"
                                }
                        ],
                        "imageUrl": "trt-tamil-olli",
                        "priority": 7
                },
                {
                        "id": 8,
                        "name": "Chellam FM",
                        "desc": "Chellam FM",
                        "genre": "Music",
                        "streams": [
                                {
                                        "src": "http://www.shoutcast.com/",
                                        "srcName": "Chellam FM",
                                        "br": "128",
                                        "url": "http://5.63.145.172:7124/;?icy=http"
                                }
                        ],
                        "imageUrl": "chellam-fm",
                        "priority": 8
                },
                {
                        "id": 9,
                        "name": "CMR Tamil",
                        "desc": "CMR Tamil",
                        "genre": "Music",
                        "streams": [
                                {
                                        "src": "http://www.shoutcast.com/",
                                        "srcName": "CMR Tamil",
                                        "br": "128",
                                        "url": "http://24.235.111.234:8010/;?icy=http"
                                }
                        ],
                        "imageUrl": "https://cmr24.net/wp-content/themes/cmr/images/logo.png",
                        "priority": 9
                },
                {
                        "id": 10,
                        "name": "Puthu Paadal Radio",
                        "desc": "Puthu Paadal Radio",
                        "genre": "Music",
                        "streams": [
                                {
                                        "src": "http://southradios.com/puthu-paadal-radio.html",
                                        "srcName": "Puthu Paadal Radio",
                                        "br": "128",
                                        "url": "http://66.55.145.43:7759/;"
                                }
                        ],
                        "imageUrl": "puthu-paadal-radio",
                        "priority": 10
                },
                {
                        "id": 11,
                        "name": "BTC Tamil FM",
                        "desc": "BTC Tamil FM",
                        "genre": "Music",
                        "streams": [
                                {
                                        "src": "http://www.shoutcast.com/",
                                        "srcName": "btc tamil fm",
                                        "br": "64",
                                        "url": " http://yp.shoutcast.com/<base>?id=<id>"
                                }
                        ],
                        "imageUrl": "btc-tamil-fm",
                        "priority": 11
                },
                {
                        "id": 12,
                        "name": "Vanavil FM",
                        "desc": "Vanavil FM",
                        "genre": "Music",
                        "streams": [
                                {
                                        "src": "http://www.shoutcast.com/",
                                        "srcName": "vanavilfm",
                                        "br": "128",
                                        "url": " http://yp.shoutcast.com/<base>?id=<id>"
                                }
                        ],
                        "imageUrl": "vanavil-fm",
                        "priority": 12
                },
                {
                        "id": 13,
                        "name": "Radio City Tamil",
                        "desc": "Radio City Tamil",
                        "genre": "Music",
                        "streams": [
                                {
                                        "src": "http://www.shoutcast.com/",
                                        "srcName": "radio city tamil",
                                        "br": "96",
                                        "url": " http://yp.shoutcast.com/<base>?id=<id>"
                                },
                                {
                                        "src": "http://www.shoutcast.com/",
                                        "srcName": "radio city tamil",
                                        "br": "128",
                                        "url": " http://yp.shoutcast.com/<base>?id=<id>"
                                }
                        ],
                        "imageUrl": "radio-city-tamil",
                        "priority": 13
                },
                {
                        "id": 14,
                        "name": "ILC Tamil",
                        "desc": "ILC Tamil",
                        "genre": "Music",
                        "streams": [
                                {
                                        "src": "http://www.shoutcast.com/",
                                        "srcName": "ilc tamil",
                                        "br": "64",
                                        "url": " http://yp.shoutcast.com/<base>?id=<id>"
                                }
                        ],
                        "imageUrl": "ilc-tamil",
                        "priority": 14
                },
                {
                        "id": 15,
                        "name": "Paris Tamil FM",
                        "desc": "Paris Tamil FM",
                        "genre": "Music",
                        "streams": [
                                {
                                        "src": "http://www.shoutcast.com/",
                                        "srcName": "paristamilfm",
                                        "br": "128",
                                        "url": " http://yp.shoutcast.com/<base>?id=<id>"
                                }
                        ],
                        "imageUrl": "paris-tamil-fm",
                        "priority": 15
                },
                {
                        "id": 16,
                        "name": "Hungama Tamil Hits",
                        "desc": "Hungama Tamil Hits",
                        "genre": "Music",
                        "streams": [
                                {
                                        "src": "http://www.shoutcast.com/",
                                        "srcName": "hungama-tamil-hits",
                                        "br": "56",
                                        "url": " http://yp.shoutcast.com/<base>?id=<id>"
                                }
                        ],
                        "imageUrl": "hungama-tamil-hits",
                        "priority": 16
                },
                {
                        "id": 17,
                        "name": "Tamil Star Radio",
                        "desc": "Tamil Star Radio",
                        "genre": "Music",
                        "streams": [
                                {
                                        "src": "http://www.shoutcast.com/",
                                        "srcName": "tamil star radio",
                                        "br": "64",
                                        "url": " http://yp.shoutcast.com/<base>?id=<id>"
                                }
                        ],
                        "imageUrl": "tamil-start-radio",
                        "priority": 17
                },
                {
                        "id": 18,
                        "name": "Tamil Isai",
                        "desc": "Tamil Isai",
                        "genre": "Music",
                        "streams": [
                                {
                                        "src": "http://www.shoutcast.com/",
                                        "srcName": "tamilisai",
                                        "br": "64",
                                        "url": " http://yp.shoutcast.com/<base>?id=<id>"
                                }
                        ],
                        "imageUrl": "tamil-isai",
                        "priority": 18
                },
                {
                        "id": 19,
                        "name": "Bakthi Malargal",
                        "desc": "Bakthi Malargal",
                        "genre": "Spiritual",
                        "streams": [
                                {
                                        "src": "http://www.shoutcast.com/",
                                        "srcName": "bakthi malargal",
                                        "br": "32",
                                        "url": " http://yp.shoutcast.com/<base>?id=<id>"
                                }
                        ],
                        "imageUrl": "bakthi-malargal",
                        "priority": 19
                },
                {
                        "id": 20,
                        "name": "Thenral World Radio",
                        "desc": "Thenral World Radio",
                        "genre": "Music",
                        "streams": [
                                {
                                        "src": "http://www.shoutcast.com/",
                                        "srcName": "thenralworldradio",
                                        "br": "64",
                                        "url": " http://yp.shoutcast.com/<base>?id=<id>"
                                }
                        ],
                        "imageUrl": "thenral-world-radio",
                        "priority": 20
                },
				{
                        "id": 21,
                        "name": "DJSiran Tamil FM",
                        "desc": "DJSiran Tamil FM",
                        "genre": "Music",
                        "streams": [
                                {
                                        "src": "http://www.shoutcast.com/",
                                        "srcName": "djsiran tamil fm",
                                        "br": "128",
                                        "url": " http://yp.shoutcast.com/<base>?id=<id>"
                                }
                        ],
                        "imageUrl": "djsiran-tamil-fm",
                        "priority": 21
                },
                {
                        "id": 22,
                        "name": "Kalasam FM",
                        "desc": "Kalasam FM",
                        "genre": "Music",
                        "streams": [
                                {
                                        "src": "http://www.shoutcast.com/",
                                        "srcName": "kalasam.com",
                                        "br": "128",
                                        "url": " http://yp.shoutcast.com/<base>?id=<id>"
                                }
                        ],
                        "imageUrl": "kalasam-fm",
                        "priority": 22
                },
                {
                        "id": 23,
                        "name": "ETR FM",
                        "desc": "ETR FM",
                        "genre": "Music",
                        "streams": [
                                {
                                        "src": "http://www.shoutcast.com/",
                                        "srcName": "etr fm",
                                        "br": "128",
                                        "url": " http://yp.shoutcast.com/<base>?id=<id>"
                                }
                        ],
                        "imageUrl": "etr-fm",
                        "priority": 23
                },
                {
                        "id": 24,
                        "name": "GTBC FM",
                        "desc": "GTBC FM",
                        "genre": "Music",
                        "streams": [
                                {
                                        "src": "http://www.shoutcast.com/",
                                        "srcName": "gtbc.fm",
                                        "br": "128",
                                        "url": " http://yp.shoutcast.com/<base>?id=<id>"
                                }
                        ],
                        "imageUrl": "gtbc-fm",
                        "priority": 24
                },
                {
                        "id": 25,
                        "name": "Ezhisai FM",
                        "desc": "Ezhisai FM",
                        "genre": "Music",
                        "streams": [
                                {
                                        "src": "http://www.shoutcast.com/",
                                        "srcName": "ezhisai fm",
                                        "br": "80",
                                        "url": " http://yp.shoutcast.com/<base>?id=<id>"
                                }
                        ],
                        "imageUrl": "ezhisai-fm",
                        "priority": 25
                },
                {
                        "id": 26,
                        "name": "Likexa FM",
                        "desc": "Likexa FM",
                        "genre": "Music",
                        "streams": [
                                {
                                        "src": "http://www.shoutcast.com/",
                                        "srcName": "likexa fm",
                                        "br": "128",
                                        "url": " http://yp.shoutcast.com/<base>?id=<id>"
                                }
                        ],
                        "imageUrl": "likexa-fm",
                        "priority": 26
                },
                {
                        "id": 27,
                        "name": "GTR FM",
                        "desc": "GTR FM",
                        "genre": "Music",
                        "streams": [
                                {
                                        "src": "http://www.shoutcast.com/",
                                        "srcName": "gtr.fm",
                                        "br": "96",
                                        "url": " http://yp.shoutcast.com/<base>?id=<id>"
                                }
                        ],
                        "imageUrl": "gtr-fm",
                        "priority": 27
                },
                {
                        "id": 28,
                        "name": "Tamil 2 FM",
                        "desc": "Tamil 2 FM",
                        "genre": "Music",
                        "streams": [
                                {
                                        "src": "http://www.shoutcast.com/",
                                        "srcName": "tamil 2 fm",
                                        "br": "48",
                                        "url": " http://yp.shoutcast.com/<base>?id=<id>"
                                }
                        ],
                        "imageUrl": "tamil-2-fm",
                        "priority": 28
                },
                {
                        "id": 29,
                        "name": "Tamilar Kural Radio",
                        "desc": "Tamilar Kural Radio",
                        "genre": "Music",
                        "streams": [
                                {
                                        "src": "http://www.shoutcast.com/",
                                        "srcName": "tamilarkural radio",
                                        "br": "128",
                                        "url": " http://yp.shoutcast.com/<base>?id=<id>"
                                }
                        ],
                        "imageUrl": "tamilar-kural-radio",
                        "priority": 29
                },
                {
                        "id": 30,
                        "name": "Harris Jayaraj Radio",
                        "desc": "Harris Jayaraj Radio",
                        "genre": "Music",
                        "streams": [
                                {
                                        "src": "http://www.shoutcast.com/",
                                        "srcName": "harris jayaraj radio",
                                        "br": "128",
                                        "url": " http://yp.shoutcast.com/<base>?id=<id>"
                                }
                        ],
                        "imageUrl": "harris-jayaraj-radio",
                        "priority": 30
                },
                {
                        "id": 31,
                        "name": "TTR Radio",
                        "desc": "TTR Radio",
                        "genre": "Music",
                        "streams": [
                                {
                                        "src": "http://www.shoutcast.com/",
                                        "srcName": "ttr radio",
                                        "br": "128",
                                        "url": " http://yp.shoutcast.com/<base>?id=<id>"
                                }
                        ],
                        "imageUrl": "ttr-radio",
                        "priority": 31
                },
                {
                        "id": 32,
                        "name": "ABC Tamil",
                        "desc": "ABC Tamil",
                        "genre": "Music",
                        "streams": [
                                {
                                        "src": "http://www.shoutcast.com/",
                                        "srcName": "abc tamil",
                                        "br": "64",
                                        "url": " http://yp.shoutcast.com/<base>?id=<id>"
                                }
                        ],
                        "imageUrl": "abc-tamil",
                        "priority": 32
                },
                {
                        "id": 33,
                        "name": "Hungama Tamil Classics",
                        "desc": "Hungama Tamil Classics",
                        "genre": "Music",
                        "streams": [
                                {
                                        "src": "http://www.shoutcast.com/",
                                        "srcName": "hungama-tamil-classics",
                                        "br": "48",
                                        "url": " http://yp.shoutcast.com/<base>?id=<id>"
                                }
                        ],
                        "imageUrl": "hungama-tamil-classics",
                        "priority": 33
                },
                {
                        "id": 34,
                        "name": "TSR Live Tamil Radio",
                        "desc": "TSR Live Tamil Radio",
                        "genre": "Music",
                        "streams": [
                                {
                                        "src": "http://www.shoutcast.com/",
                                        "srcName": "tsrlive tamil radio",
                                        "br": "128",
                                        "url": " http://yp.shoutcast.com/<base>?id=<id>"
                                }
                        ],
                        "imageUrl": "tsrlive-tamil-radio",
                        "priority": 34
                },
                {
                        "id": 35,
                        "name": "Tamil Mirror Radio",
                        "desc": "Tamil Mirror Radio",
                        "genre": "Music",
                        "streams": [
                                {
                                        "src": "http://www.shoutcast.com/",
                                        "srcName": "tamil mirror radio",
                                        "br": "64",
                                        "url": " http://yp.shoutcast.com/<base>?id=<id>"
                                }
                        ],
                        "imageUrl": "tamil-mirror-radio",
                        "priority": 35
                }
        ]
}